[
  {
    "timestamp": "2025-04-14T20:27:41.530Z",
    "source": "new_vehicle_finance",
    "url": "https://www.ovms.co.uk/used-car-details/used-volkswagen-caddy-20-tdi-c20-startline-panel-va-manual-diesel/id-202311013527969/",
    "dealer_id": "1504",
    "car_id": "22362929",
    "data": [
      {
        "type": "vehicle",
        "registration_number": "EF18XSE",
        "registration_date": "10/08/2018",
        "mileage": 74696,
        "status": "Used"
      },
      {
        "type": "finance_hp",
        "name": "HP",
        "finance_type": "Hire Purchase",
        "cash_price": 11580,
        "total_price": 11580,
        "deposit": 1000,
        "balance": 10580,
        "apr": 12.9,
        "rate_of_interest": 12.17,
        "term": 60,
        "regular_payment": 236.39,
        "final_payment": 236.39,
        "total_amount_payable": 15183.4,
        "total_charge_for_credit": 3603.4,
        "amount_of_credit": 10580,
        "lender": "Black Horse Limited",
        "annual_mileage": 10000,
        "excess_mileage_rate": 0,
        "residual": 0
      }
    ]
  }
]