[
  {
    "timestamp": "2025-05-15T16:28:27.526Z",
    "source": "new_vehicle_finance",
    "url": "https://www.stoughtoncarsales.co.uk/used-skoda-kamiq-godalming-surrey-6648705",
    "dealer_id": "1994",
    "car_id": "26877387",
    "data": [
      {
        "type": "vehicle",
        "registration_number": "HK22BMY",
        "registration_date": "30/06/2022",
        "mileage": 39133,
        "status": "Used"
      },
      {
        "type": "finance_hp",
        "name": "HP",
        "finance_type": "Hire Purchase",
        "cash_price": 16500,
        "total_price": 16500,
        "deposit": 1650,
        "balance": 14850,
        "apr": 11.9,
        "rate_of_interest": 6.27,
        "term": 60,
        "regular_payment": 325.06,
        "final_payment": 326.06,
        "total_amount_payable": 21154.6,
        "total_charge_for_credit": 4654.6,
        "amount_of_credit": 14850,
        "lender": "Motonovo Finance Limited",
        "annual_mileage": 10000,
        "excess_mileage_rate": 0,
        "residual": 0
      },
      {
        "type": "finance_pcp",
        "name": "PCP",
        "finance_type": "PCP",
        "cash_price": 16500,
        "total_price": 16500,
        "deposit": 1650,
        "balance": 14850,
        "apr": 11.9,
        "rate_of_interest": 5.8,
        "term": 49,
        "regular_payment": 261.55,
        "final_payment": 7575.29,
        "total_amount_payable": 21779.69,
        "total_charge_for_credit": 5279.69,
        "amount_of_credit": 14850,
        "lender": "Motonovo Finance Limited",
        "annual_mileage": 10000,
        "contract_mileage": 40833,
        "excess_mileage_rate": 0.1,
        "residual": 7574.29,
        "price_to_buy": 7575.29
      }
    ]
  }
]