[
  {
    "timestamp": "2025-04-15T00:50:01.719Z",
    "source": "new_vehicle_finance",
    "url": "https://www.priddysmotorcompany.co.uk/cars/mini/hatch/2.0-3-door-hatch-cooper-s-sport-jcwjohn-cooper-works-styling/1409655/",
    "dealer_id": "6287",
    "car_id": "27409830",
    "data": [
      {
        "type": "vehicle",
        "registration_number": "WP68WPX",
        "registration_date": "24/12/2018",
        "mileage": 34785,
        "status": "Used"
      },
      {
        "type": "finance_hp",
        "name": "HP",
        "finance_type": "Hire Purchase",
        "cash_price": 16470,
        "total_price": 16470,
        "deposit": 1647,
        "balance": 14823,
        "apr": 10.9,
        "rate_of_interest": 5.73,
        "term": 60,
        "regular_payment": 317.79,
        "final_payment": 318.79,
        "total_amount_payable": 20715.4,
        "total_charge_for_credit": 4245.4,
        "amount_of_credit": 14823,
        "lender": "Motonovo Finance Limited",
        "annual_mileage": 10000,
        "excess_mileage_rate": 0,
        "residual": 0
      }
    ]
  }
]