[
  {
    "timestamp": "2025-04-14T19:09:49.754Z",
    "source": "new_vehicle_finance",
    "url": "https://www.llanellimotorcompany.co.uk/used-vehicle-details/Skoda-Fabia-U8507/",
    "dealer_id": "7446",
    "car_id": "21277089",
    "data": [
      {
        "type": "vehicle",
        "registration_number": "CP67CNU",
        "registration_date": "24/11/2017",
        "mileage": 36371,
        "status": "Used"
      },
      {
        "type": "finance_hp",
        "name": "HP",
        "finance_type": "Hire Purchase",
        "cash_price": 8995,
        "total_price": 8995,
        "deposit": 899.5,
        "balance": 8095.5,
        "apr": 9.9,
        "rate_of_interest": 5.14,
        "term": 48,
        "regular_payment": 203.3,
        "final_payment": 204.3,
        "total_amount_payable": 10658.9,
        "total_charge_for_credit": 1663.9,
        "amount_of_credit": 8095.5,
        "lender": "Admiral Car Finance",
        "annual_mileage": 10000,
        "excess_mileage_rate": 0,
        "residual": 0
      }
    ]
  }
]