[
  {
    "timestamp": "2025-05-15T15:28:14.537Z",
    "source": "codeweavers_calculator",
    "url": "https://www.sjamesprestige.com/used-mercedes-benz-e-class-essendine-lincolnshire-6537440",
    "dealer_id": "6814",
    "car_id": "26445765",
    "data": [
      {
        "type": "vehicle",
        "manufacturer": "Mercedes-Benz",
        "model": "E-Class",
        "variant": "DIESEL ESTATE",
        "derivative": "E300de AMG Line Edition 9G-Tronic",
        "registration_number": "OE21ZJZ",
        "registration_date": "29/07/2021",
        "mileage": 49450,
        "status": "PreOwned"
      },
      {
        "type": "finance_pcp",
        "name": "PCP",
        "finance_type": "PCP",
        "cash_price": 23750,
        "total_price": 23750,
        "deposit": 2375,
        "balance": 21375,
        "apr": 11.4,
        "rate_of_interest": 11.4,
        "term": 49,
        "regular_payment": 364.65,
        "final_payment": 11227.09,
        "total_amount_payable": 31105.29,
        "total_charge_for_credit": 7355.29,
        "amount_of_credit": 21375,
        "lender": "Alphera Financial Services",
        "annual_mileage": 10000,
        "contract_mileage": 40833,
        "excess_mileage_rate": 6.24,
        "residual": 11227.09,
        "price_to_buy": 11227.09
      },
      {
        "type": "finance_hp",
        "name": "HP",
        "finance_type": "Hire Purchase",
        "cash_price": 23750,
        "total_price": 23750,
        "deposit": 2375,
        "balance": 21375,
        "apr": 11.4,
        "rate_of_interest": 11.4,
        "term": 60,
        "regular_payment": 463.07,
        "final_payment": 464.07,
        "total_amount_payable": 30160.2,
        "total_charge_for_credit": 6410.2,
        "amount_of_credit": 21375,
        "lender": "Alphera Financial Services",
        "annual_mileage": 10000,
        "excess_mileage_rate": 0,
        "residual": 0
      }
    ]
  }
]