[
  {
    "timestamp": "2025-04-10T05:25:02.690Z",
    "source": "codeweavers_calculator",
    "url": "https://www.premiermotorcollection.co.uk/vehicle-details/used-vauxhall-astra-i-life-for-sale-u1425/",
    "dealer_id": "4019",
    "car_id": "24049795",
    "data": [
      {
        "type": "vehicle",
        "manufacturer": "Vauxhall",
        "model": "ASTRA",
        "variant": "HATCHBACK",
        "derivative": "1.4i 16V Life",
        "registration_number": "DE59VUS",
        "registration_date": "10/11/2009",
        "mileage": 105000,
        "status": "PreOwned"
      },
      {
        "type": "finance_cs",
        "name": "CS",
        "finance_type": "Conditional Sale",
        "cash_price": 1500,
        "total_price": 1500,
        "deposit": 500,
        "balance": 1000,
        "apr": 10.9,
        "rate_of_interest": 5.57,
        "term": 60,
        "regular_payment": 21.31,
        "final_payment": 31.31,
        "total_amount_payable": 1788.6,
        "total_charge_for_credit": 288.6,
        "amount_of_credit": 1000,
        "lender": "Close Motor Finance"
      }
    ]
  }
]