[
  {
    "timestamp": "2025-04-10T07:04:34.359Z",
    "source": "codeweavers_calculator",
    "url": "https://www.idealmotorco.co.uk/details/used-car-in-wigan/honda/civic/1.0-vtec-turbo-sr-euro-6-ss-5dr/1348969/",
    "dealer_id": "4338",
    "car_id": "26685149",
    "data": [
      {
        "type": "vehicle",
        "manufacturer": "Honda",
        "model": "CIVIC",
        "variant": "HATCHBACK",
        "derivative": "1.0 VTEC Turbo 126 SR",
        "registration_number": "DA68EYH",
        "registration_date": "14/11/2018",
        "mileage": 20545,
        "status": "PreOwned"
      },
      {
        "type": "finance_pcp",
        "name": "PCP",
        "finance_type": "PCP",
        "cash_price": 11990,
        "total_price": 11990,
        "deposit": 1199,
        "balance": 10791,
        "apr": 8.9,
        "rate_of_interest": 8.9,
        "term": 43,
        "regular_payment": 189.9,
        "final_payment": 5320.29,
        "total_amount_payable": 14495.09,
        "total_charge_for_credit": 2505.09,
        "amount_of_credit": 10791,
        "lender": "Auto Union Finance Ltd.",
        "annual_mileage": 10000,
        "contract_mileage": 35833,
        "excess_mileage_rate": 3.82,
        "residual": 5319.29,
        "price_to_buy": 5320.29
      },
      {
        "type": "finance_hp",
        "name": "HP",
        "finance_type": "Hire Purchase",
        "cash_price": 11990,
        "total_price": 11990,
        "deposit": 1199,
        "balance": 10791,
        "apr": 8.9,
        "rate_of_interest": 8.9,
        "term": 60,
        "regular_payment": 221.67,
        "final_payment": 222.67,
        "total_amount_payable": 14500.2,
        "total_charge_for_credit": 2510.2,
        "amount_of_credit": 10791,
        "lender": "Auto Union Finance Ltd.",
        "annual_mileage": 10000,
        "excess_mileage_rate": 0,
        "residual": 0
      }
    ]
  }
]