[
  {
    "timestamp": "2025-04-10T22:59:09.505Z",
    "source": "codeweavers_calculator",
    "url": "https://www.grcarter-motors.co.uk/used-cars/ford-focus-10t-ecoboost-zetec-s-s-5dr-V1827",
    "dealer_id": "4368",
    "car_id": "26311335",
    "data": [
      {
        "type": "vehicle",
        "manufacturer": "Ford",
        "model": "FOCUS",
        "variant": "HATCHBACK",
        "derivative": "1.0 125 EcoBoost Zetec",
        "registration_number": "BK64LNN",
        "registration_date": "24/09/2014",
        "mileage": 11000,
        "status": "PreOwned"
      },
      {
        "type": "finance_hp",
        "name": "HP",
        "finance_type": "Hire Purchase",
        "cash_price": 7295,
        "total_price": 7295,
        "deposit": 729.5,
        "balance": 6565.5,
        "apr": 12.9,
        "rate_of_interest": 6.63,
        "term": 36,
        "regular_payment": 218.65,
        "final_payment": 219.65,
        "total_amount_payable": 8601.9,
        "total_charge_for_credit": 1306.9,
        "amount_of_credit": 6565.5,
        "lender": "CarFinance247 Limited",
        "annual_mileage": 10000,
        "excess_mileage_rate": 0,
        "residual": 0
      }
    ]
  }
]