[
  {
    "timestamp": "2025-04-11T04:16:08.623Z",
    "source": "codeweavers_calculator",
    "url": "https://www.tallisofbath.com/vehicle-details/used-mercedes-benz-c-class-c250-bluetec-sport-for-sale-u1823/",
    "dealer_id": "5408",
    "car_id": "27195566",
    "data": [
      {
        "type": "vehicle",
        "manufacturer": "Mercedes-Benz",
        "model": "C-Class",
        "variant": "DIESEL ESTATE",
        "derivative": "C250 BlueTEC Sport Premium",
        "registration_number": "HV64AHJ",
        "registration_date": "17/09/2014",
        "mileage": 134000,
        "status": "PreOwned"
      },
      {
        "type": "finance_hp",
        "name": "HP",
        "finance_type": "Conditional Sale",
        "cash_price": 9950,
        "total_price": 9950,
        "deposit": 995,
        "balance": 8955,
        "apr": 11.9,
        "rate_of_interest": 6.25,
        "term": 60,
        "regular_payment": 195.89,
        "final_payment": 205.89,
        "total_amount_payable": 12758.4,
        "total_charge_for_credit": 2808.4,
        "amount_of_credit": 8955,
        "lender": "Close Motor Finance"
      }
    ]
  }
]