[
  {
    "timestamp": "2025-04-11T05:28:50.008Z",
    "source": "codeweavers_calculator",
    "url": "https://www.richtoy.co.uk/details/used-car-in-scunthorpe/lexus/nx/2.5-300h-takumi-e-cvt-4wd-euro-6-ss-5dr/1392997/",
    "dealer_id": "5642",
    "car_id": "27203272",
    "data": [
      {
        "type": "vehicle",
        "manufacturer": "Unknown",
        "model": "",
        "variant": "",
        "derivative": "",
        "registration_number": "PL69YVJ",
        "registration_date": "02/09/2019",
        "mileage": 42240,
        "status": "PreOwned"
      },
      {
        "type": "finance_cs",
        "name": "CS",
        "finance_type": "Conditional Sale",
        "cash_price": 26650,
        "total_price": 26650,
        "deposit": 2665,
        "balance": 23985,
        "apr": 10.9,
        "rate_of_interest": 5.72,
        "term": 60,
        "regular_payment": 514.08,
        "final_payment": 524.08,
        "total_amount_payable": 33519.8,
        "total_charge_for_credit": 6869.8,
        "amount_of_credit": 23985,
        "lender": "Close Motor Finance"
      }
    ]
  }
]