[
  {
    "timestamp": "2025-04-11T16:31:13.027Z",
    "source": "codeweavers_calculator",
    "url": "https://www.moyautoservices.com/used-porsche-cayenne-dungannon-county-tyrone-6502949",
    "dealer_id": "6120",
    "car_id": "27388621",
    "data": [
      {
        "type": "vehicle",
        "manufacturer": "Porsche",
        "model": "CAYENNE",
        "variant": "COUPE SPECIAL EDITIONS",
        "derivative": "E-Hybrid Platinum Edition Tiptronic S",
        "registration_number": "VO23XHU",
        "registration_date": "28/03/2023",
        "mileage": 10000,
        "status": "PreOwned"
      },
      {
        "type": "finance_pcp",
        "name": "PCP",
        "finance_type": "PCP",
        "cash_price": 73995,
        "total_price": 73995,
        "deposit": 7399,
        "balance": 66596,
        "apr": 9.9,
        "rate_of_interest": 9.48,
        "term": 49,
        "regular_payment": 1106.3,
        "final_payment": 33143.5,
        "total_amount_payable": 93644.9,
        "total_charge_for_credit": 19649.9,
        "amount_of_credit": 66596,
        "lender": "Mann Island Finance",
        "annual_mileage": 10000,
        "contract_mileage": 40000,
        "excess_mileage_rate": 22,
        "residual": 33142.5,
        "price_to_buy": 33143.5
      },
      {
        "type": "finance_hp",
        "name": "HP",
        "finance_type": "Hire Purchase",
        "cash_price": 73995,
        "total_price": 73995,
        "deposit": 7399,
        "balance": 66596,
        "apr": 9.9,
        "rate_of_interest": 9.48,
        "term": 60,
        "regular_payment": 1397.89,
        "final_payment": 1398.89,
        "total_amount_payable": 91273.4,
        "total_charge_for_credit": 17278.4,
        "amount_of_credit": 66596,
        "lender": "Mann Island Finance",
        "annual_mileage": 10000,
        "excess_mileage_rate": 0,
        "residual": 0
      }
    ]
  }
]