[
  {
    "timestamp": "2025-04-11T16:56:24.175Z",
    "source": "codeweavers_calculator",
    "url": "https://www.hammondgroup.co.uk/used/ford/ranger/pick-up-dcab-wildtrak-30-ecoblue-v6-240-auto/halesworth/suffolk/243390",
    "dealer_id": "6215",
    "car_id": "27377881",
    "data": [
      {
        "type": "vehicle",
        "manufacturer": "Ford",
        "model": "RANGER",
        "variant": "DIESEL",
        "derivative": "Pick Up D/Cab Wildtrak 3.0 EcoBlue V6 240",
        "registration_number": "XX25XXX",
        "registration_date": "06/03/2025",
        "mileage": 400,
        "status": "PreOwned"
      },
      {
        "type": "finance_hp",
        "name": "HP",
        "finance_type": "Hire Purchase",
        "cash_price": 55794,
        "total_price": 55794,
        "deposit": 11799,
        "balance": 43995,
        "apr": 10.9,
        "rate_of_interest": 5.72,
        "term": 60,
        "regular_payment": 942.96,
        "final_payment": 952.96,
        "total_amount_payable": 68386.6,
        "total_charge_for_credit": 12592.6,
        "amount_of_credit": 43995,
        "lender": "Northridge Finance",
        "annual_mileage": 10000,
        "excess_mileage_rate": 0,
        "residual": 0
      }
    ]
  }
]