[
  {
    "timestamp": "2025-04-11T15:09:23.511Z",
    "source": "codeweavers_calculator",
    "url": "https://www.carplugmcr.co.uk/vehicle-details/used-bmw-x3-20d-m-sport-for-sale-in-manchester-u1906/",
    "dealer_id": "6992",
    "car_id": "26387521",
    "data": [
      {
        "type": "vehicle",
        "manufacturer": "BMW",
        "model": "X3",
        "variant": "DIESEL ESTATE",
        "derivative": "xDrive20d M Sport Step",
        "registration_number": "WD16SKJ",
        "registration_date": "30/06/2016",
        "mileage": 91887,
        "status": "PreOwned"
      },
      {
        "type": "finance_cs_close",
        "name": "CS_CLOSE",
        "finance_type": "Conditional Sale",
        "cash_price": 11995,
        "total_price": 11995,
        "deposit": 1199.5,
        "balance": 10795.5,
        "apr": 10.9,
        "rate_of_interest": 5.71,
        "term": 60,
        "regular_payment": 231.29,
        "final_payment": 241.29,
        "total_amount_payable": 15086.9,
        "total_charge_for_credit": 3091.9,
        "amount_of_credit": 10795.5,
        "lender": "Close Motor Finance"
      }
    ]
  }
]