[
  {
    "timestamp": "2025-04-11T15:14:59.327Z",
    "source": "codeweavers_calculator",
    "url": "https://www.samperformance.co.uk/cars/mercedes-benz/eclass/4.0-e63-v8-biturbo-amg-s/1333603/",
    "dealer_id": "6997",
    "car_id": "26488773",
    "data": [
      {
        "type": "vehicle",
        "manufacturer": "Mercedes-Benz",
        "model": "E-Class",
        "variant": "E-Class AMG Saloon",
        "derivative": "E63 S AMG Prem Plus Sal Auto 4MATIC+ MY19 2018",
        "registration_number": "AJ19HWW",
        "registration_date": "17/04/2019",
        "mileage": 58100,
        "status": "PreOwned"
      },
      {
        "type": "finance_hp",
        "name": "HP",
        "finance_type": "Conditional Sale",
        "cash_price": 45995,
        "total_price": 45995,
        "deposit": 4599.5,
        "balance": 41395.5,
        "apr": 8.9,
        "rate_of_interest": 4.65,
        "term": 60,
        "regular_payment": 850.33,
        "final_payment": 860.33,
        "total_amount_payable": 55629.3,
        "total_charge_for_credit": 9634.3,
        "amount_of_credit": 41395.5,
        "lender": "Close Motor Finance"
      }
    ]
  }
]