[
  {
    "timestamp": "2025-04-11T21:28:21.486Z",
    "source": "codeweavers_calculator",
    "url": "https://www.rosespecialistcars.co.uk/details/specialist-car-in-quainton/audi/s4/3.0-tfsi-v6-tiptronic-quattro-euro-6-ss-5dr/1257916/",
    "dealer_id": "9048",
    "car_id": "25571476",
    "data": [
      {
        "type": "vehicle",
        "manufacturer": "Audi",
        "model": "A4",
        "variant": "AVANT",
        "derivative": "S4 Quattro Tip Tronic",
        "registration_number": "YG68FMX",
        "registration_date": "06/09/2018",
        "mileage": 41000,
        "status": "PreOwned"
      },
      {
        "type": "finance_hp",
        "name": "HP",
        "finance_type": "Conditional Sale",
        "cash_price": 28600,
        "total_price": 28600,
        "deposit": 2860,
        "balance": 25740,
        "apr": 10.9,
        "rate_of_interest": 5.72,
        "term": 60,
        "regular_payment": 551.69,
        "final_payment": 561.69,
        "total_amount_payable": 35971.4,
        "total_charge_for_credit": 7371.4,
        "amount_of_credit": 25740,
        "lender": "Close Motor Finance"
      }
    ]
  }
]