[
  {
    "timestamp": "2025-04-09T12:35:46.188Z",
    "source": "codeweavers_calculator",
    "url": "https://www.southgrovemotorcompany.co.uk/used-citroen-ds3-bolton-lancashire-5327557",
    "dealer_id": "59",
    "car_id": "25961708",
    "data": [
      {
        "type": "vehicle",
        "manufacturer": "Citroen",
        "model": "DS3",
        "variant": "DIESEL HATCHBACK",
        "derivative": "1.6 e-HDi Airdream DStyle Plus",
        "registration_number": "NJ61XYX",
        "registration_date": "27/01/2012",
        "mileage": 83000,
        "status": "PreOwned"
      },
      {
        "type": "finance_hp",
        "name": "HP",
        "finance_type": "Conditional Sale",
        "cash_price": 3989,
        "total_price": 3989,
        "deposit": 1000,
        "balance": 2989,
        "apr": 18,
        "rate_of_interest": 6.5,
        "term": 60,
        "regular_payment": 73.74,
        "final_payment": 73.74,
        "total_amount_payable": 5424.4,
        "total_charge_for_credit": 1435.4,
        "amount_of_credit": 2989,
        "lender": "Close Motor Finance"
      }
    ]
  }
]