[
  {
    "timestamp": "2025-05-13T07:08:29.176Z",
    "source": "new_vehicle_finance",
    "url": "https://www.smvcommercials.co.uk/vehicle-details/used-volkswagen-transporter-fridge-van-2-0tdi-t28-bluemotion-tech-trendline-for-sale-smv-car-lcv-u225/",
    "dealer_id": "2612",
    "car_id": "23773496",
    "data": [
      {
        "type": "vehicle",
        "registration_number": "WO68KHZ",
        "registration_date": "13/02/2019",
        "mileage": 153249,
        "status": "Used"
      }
    ]
  }
]